<annotation>
	<folder>data</folder>
	<filename>33.jpg</filename>
	<path>F:\新建文件夹\Tencent Files\1530087345\FileRecv\data\33.jpg</path>
	<source>
		<database>Unknown</database>
	</source>
	<size>
		<width>720</width>
		<height>1280</height>
		<depth>3</depth>
	</size>
	<segmented>0</segmented>
	<object>
		<name>front</name>
		<pose>Unspecified</pose>
		<truncated>0</truncated>
		<difficult>0</difficult>
		<bndbox>
			<xmin>131</xmin>
			<ymin>230</ymin>
			<xmax>648</xmax>
			<ymax>344</ymax>
		</bndbox>
	</object>
	<object>
		<name>pocket</name>
		<pose>Unspecified</pose>
		<truncated>0</truncated>
		<difficult>0</difficult>
		<bndbox>
			<xmin>188</xmin>
			<ymin>271</ymin>
			<xmax>352</xmax>
			<ymax>330</ymax>
		</bndbox>
	</object>
	<object>
		<name>pocket</name>
		<pose>Unspecified</pose>
		<truncated>0</truncated>
		<difficult>0</difficult>
		<bndbox>
			<xmin>404</xmin>
			<ymin>273</ymin>
			<xmax>566</xmax>
			<ymax>337</ymax>
		</bndbox>
	</object>
</annotation>
