<annotation>
	<folder>data</folder>
	<filename>82.jpg</filename>
	<path>F:\新建文件夹\Tencent Files\1530087345\FileRecv\data\82.jpg</path>
	<source>
		<database>Unknown</database>
	</source>
	<size>
		<width>720</width>
		<height>1280</height>
		<depth>3</depth>
	</size>
	<segmented>0</segmented>
	<object>
		<name>front</name>
		<pose>Unspecified</pose>
		<truncated>0</truncated>
		<difficult>0</difficult>
		<bndbox>
			<xmin>23</xmin>
			<ymin>371</ymin>
			<xmax>444</xmax>
			<ymax>508</ymax>
		</bndbox>
	</object>
	<object>
		<name>pocket</name>
		<pose>Unspecified</pose>
		<truncated>0</truncated>
		<difficult>0</difficult>
		<bndbox>
			<xmin>127</xmin>
			<ymin>414</ymin>
			<xmax>224</xmax>
			<ymax>465</ymax>
		</bndbox>
	</object>
	<object>
		<name>pocket</name>
		<pose>Unspecified</pose>
		<truncated>0</truncated>
		<difficult>0</difficult>
		<bndbox>
			<xmin>273</xmin>
			<ymin>433</ymin>
			<xmax>356</xmax>
			<ymax>484</ymax>
		</bndbox>
	</object>
</annotation>
